[{"id":"4b673893.b788f8","type":"tab","label":"Company Turnover","disabled":false,"info":""},{"id":"b222f09b.a4f4","type":"ui_form","z":"4b673893.b788f8","name":"","label":"","group":"acf40ca2.a7642","order":0,"width":0,"height":0,"options":[{"label":"Revenue","value":"rev","type":"number","required":true},{"label":"Sales","value":"sale","type":"number","required":true},{"label":"Marketing Spent","value":"ms","type":"number","required":true},{"label":"Administration","value":"ad","type":"number","required":true},{"label":"R&D spent","value":"rd","type":"number","required":true}],"formValue":{"rev":"","sale":"","ms":"","ad":"","rd":""},"payload":"","submit":"submit","cancel":"cancel","topic":"","x":117.5,"y":257,"wires":[["37f641d4.601b9e"]]},{"id":"37f641d4.601b9e","type":"function","z":"4b673893.b788f8","name":"Input","func":"global.set(\"rev\",msg.payload.rev);\nglobal.set(\"sale\",msg.payload.sale);\nglobal.set(\"ms\",msg.payload.ms);\nglobal.set(\"ad\",msg.payload.ad);\nglobal.set(\"rd\",msg.payload.rd);\n\nreturn msg;","outputs":1,"noerr":0,"x":304.5,"y":191,"wires":[["46b74f12.e11da"]]},{"id":"c229da06.5f59c8","type":"debug","z":"4b673893.b788f8","name":"","active":true,"tosidebar":true,"console":false,"tostatus":false,"complete":"payload","targetType":"msg","x":644.5,"y":372,"wires":[]},{"id":"46b74f12.e11da","type":"http request","z":"4b673893.b788f8","name":"","method":"GET","ret":"obj","paytoqs":false,"url":"https://eu-gb.ml.cloud.ibm.com/v3/identity/token","tls":"","proxy":"","authType":"basic","x":444,"y":267,"wires":[["c229da06.5f59c8","d12e8398.1452d"]]},{"id":"d12e8398.1452d","type":"function","z":"4b673893.b788f8","name":"Parsing_value_to_model","func":"var token=msg.payload.token;\nvar c1=global.get(\"c1\");\nvar c2=global.get(\"c2\");\nvar rev=global.get(\"rev\");\nvar sale=global.get(\"sale\");\nvar rd=global.get(\"rd\");\nvar ms=global.get(\"ms\");\nvar ad=global.get(\"ad\");\n\nmsg.payload={fields:[\"car1\",\"car2\",\"R&D spent\",\"Administration\",\"Marketing Spent\",\"Revenue\",\"Sales\"],\"values\":[[c1,c2,rd,ad,ms,rev,sale]]};\nmsg.headers={'Authorization':'Bearer'+token};\nreturn msg;","outputs":1,"noerr":0,"x":633,"y":158,"wires":[["dad93116.7a44b"]]},{"id":"dad93116.7a44b","type":"http request","z":"4b673893.b788f8","name":"","method":"POST","ret":"obj","paytoqs":false,"url":"https://eu-gb.ml.cloud.ibm.com/v3/wml_instances/921b4e0f-5957-4d27-aee4-ebc3a5d70714/deployments/b1f408f0-ac66-4ad3-aba9-f8a6e53825a9/online","tls":"","proxy":"","authType":"basic","x":718,"y":277,"wires":[["33409fea.a6ced","45b22868.d64b38"]]},{"id":"33409fea.a6ced","type":"debug","z":"4b673893.b788f8","name":"","active":true,"tosidebar":true,"console":false,"tostatus":false,"complete":"payload","targetType":"msg","x":901,"y":200,"wires":[]},{"id":"45b22868.d64b38","type":"function","z":"4b673893.b788f8","name":"","func":"msg.payload=msg.payload.values[0][0];\nreturn msg;\n","outputs":1,"noerr":0,"x":882,"y":376,"wires":[["30d6e40.2e53c1c"]]},{"id":"30d6e40.2e53c1c","type":"ui_text","z":"4b673893.b788f8","group":"acf40ca2.a7642","order":2,"width":0,"height":0,"name":"","label":"Turnover","format":"{{msg.payload}}","layout":"row-spread","x":1096,"y":273,"wires":[]},{"id":"30965542.ca2f7a","type":"ui_dropdown","z":"4b673893.b788f8","name":"","label":"","tooltip":"","place":"Select option","group":"acf40ca2.a7642","order":0,"width":0,"height":0,"passthru":true,"options":[{"label":"Maruti","value":"Maruti","type":"str"},{"label":"Renault","value":"Renault","type":"str"},{"label":"Hyundai","value":"Hyundai","type":"str"}],"payload":"","topic":"","x":165,"y":355,"wires":[["eaea6af6.229fa8"]]},{"id":"eaea6af6.229fa8","type":"function","z":"4b673893.b788f8","name":"","func":"if(msg.payload==\"Maruti\")\n{\n    global.set(\"c1\",1)\n    global.set(\"c2\",0)\n}\nelse if(msg.payload==\"Hyundai\")\n{\n    global.set(\"c1\",0)\n    global.set(\"c2\",1)\n}\nelse {\n    global.set(\"c1\",0)\n    global.set(\"c2\",0)\n}\nreturn msg;","outputs":1,"noerr":0,"x":309,"y":430,"wires":[["406fb723.eccfb8"]]},{"id":"406fb723.eccfb8","type":"debug","z":"4b673893.b788f8","name":"","active":true,"tosidebar":true,"console":false,"tostatus":false,"complete":"payload","targetType":"msg","x":477,"y":473,"wires":[]},{"id":"acf40ca2.a7642","type":"ui_group","z":"","name":"company turnover","tab":"3226c85.2dbbc38","disp":true,"width":"6","collapse":false},{"id":"3226c85.2dbbc38","type":"ui_tab","z":"","name":"AI","icon":"dashboard","disabled":false,"hidden":false}]